pypitk/.DS_Store
pypitk/__init__.py
pypitk/__main__.py
pypitk/constants.py
pypitk/init/__init__.py
pypitk/init/content.py
pypitk/init/paths.py
pypitk/init/util.py
pypitk/init_placeholder.py
pypitk/objects.py
pypitk/pydantic_model.py
pypitk/resources/.DS_Store
pypitk/resources/example_config.txt
pypitk/runtime.py
pypitk/tasks/__init__.py
pypitk/tasks/build_pypipackage.py
pypitk/tasks/update_pypipackage.py
pypitk-1.0.8.dist-info/LICENSE
pypitk-1.0.8.dist-info/WHEEL
pypitk-1.0.8.dist-info/METADATA
pypitk-1.0.8.dist-info/RECORD
