Metadata-Version: 2.1
Name: pypitk
Version: 1.0.8
Summary: pypi toolkit to build, publish and update pypi packages
License: MIT
Author: wayfaring-stranger
Author-email: zw6p226m@duck.com
Requires-Python: >=3.7,<4.0
Classifier: License :: OSI Approved :: MIT License
Classifier: Programming Language :: Python :: 3
Classifier: Programming Language :: Python :: 3.7
Classifier: Programming Language :: Python :: 3.8
Classifier: Programming Language :: Python :: 3.9
Classifier: Programming Language :: Python :: 3.10
